<?xml version="1.0" encoding="windows-1251" ?>
<markers>
  <m tm="" al="1197" lg="6.631553" lt="45.851670" />
  <m tm="" al="1307" lg="6.626652" lt="45.846819" />
  <m tm="" al="1308" lg="6.624035" lt="45.843375" />
  <m tm="" al="1309" lg="6.623048" lt="45.842299" />
  <m tm="" al="1309" lg="6.620923" lt="45.840886" />
  <m tm="" al="1310" lg="6.619962" lt="45.839331" />
  <m tm="" al="1311" lg="6.618882" lt="45.838256" />
  <m tm="" al="1311" lg="6.616464" lt="45.836212" />
  <m tm="" al="1624" lg="6.616401" lt="45.835898" />
  <m tm="" al="1647" lg="6.615280" lt="45.833685" />
  <m tm="" al="1650" lg="6.615152" lt="45.833712" />
  <m tm="" al="1651" lg="6.615261" lt="45.833533" />
  <m tm="" al="1651" lg="6.613896" lt="45.832882" />
  <m tm="" al="1772" lg="6.614177" lt="45.832204" />
  <m tm="" al="1757" lg="6.613887" lt="45.831701" />
  <m tm="" al="1746" lg="6.613488" lt="45.830315" />
  <m tm="" al="1745" lg="6.613687" lt="45.829707" />
  <m tm="" al="1738" lg="6.614580" lt="45.829162" />
  <m tm="" al="1734" lg="6.614838" lt="45.828788" />
  <m tm="" al="1733" lg="6.614755" lt="45.828270" />
  <m tm="" al="1731" lg="6.614836" lt="45.827687" />
  <m tm="" al="1714" lg="6.614618" lt="45.827546" />
  <m tm="" al="1705" lg="6.613873" lt="45.827480" />
  <m tm="" al="1700" lg="6.613374" lt="45.827329" />
  <m tm="" al="1690" lg="6.612657" lt="45.827643" />
  <m tm="" al="1683" lg="6.611740" lt="45.827596" />
  <m tm="" al="1635" lg="6.610771" lt="45.827708" />
  <m tm="" al="1622" lg="6.610179" lt="45.827882" />
  <m tm="" al="1617" lg="6.609258" lt="45.827887" />
  <m tm="" al="1612" lg="6.608642" lt="45.827994" />
  <m tm="" al="1609" lg="6.607945" lt="45.828397" />
  <m tm="" al="1603" lg="6.608316" lt="45.828851" />
  <m tm="" al="1880" lg="6.615985" lt="45.824022" />
  <m tm="" al="1881" lg="6.616532" lt="45.823339" />
  <m tm="" al="1880" lg="6.616732" lt="45.823439" />
  <m tm="" al="1880" lg="6.616707" lt="45.823680" />
  <m tm="" al="1882" lg="6.616736" lt="45.823383" />
  <m tm="" al="1883" lg="6.616931" lt="45.823253" />
  <m tm="" al="1871" lg="6.617676" lt="45.822286" />
  <m tm="" al="1871" lg="6.617721" lt="45.822085" />
  <m tm="" al="1861" lg="6.618654" lt="45.821690" />
  <m tm="" al="1860" lg="6.618113" lt="45.821599" />
  <m tm="" al="1854" lg="6.619766" lt="45.821886" />
  <m tm="" al="1842" lg="6.620984" lt="45.821764" />
  <m tm="" al="1831" lg="6.620818" lt="45.822011" />
  <m tm="" al="1827" lg="6.620864" lt="45.822214" />
  <m tm="" al="1818" lg="6.621115" lt="45.822457" />
  <m tm="" al="1810" lg="6.621560" lt="45.822553" />
  <m tm="" al="1800" lg="6.621254" lt="45.823002" />
  <m tm="" al="1793" lg="6.622150" lt="45.823904" />
  <m tm="" al="1779" lg="6.621656" lt="45.823892" />
  <m tm="" al="1778" lg="6.621733" lt="45.824020" />
  <m tm="" al="1773" lg="6.621646" lt="45.824505" />
  <m tm="" al="1772" lg="6.621750" lt="45.825016" />
  <m tm="" al="1771" lg="6.622215" lt="45.825489" />
  <m tm="" al="1759" lg="6.622225" lt="45.825818" />
  <m tm="" al="1739" lg="6.623171" lt="45.826297" />
  <m tm="" al="1720" lg="6.623789" lt="45.827072" />
  <m tm="" al="1684" lg="6.623791" lt="45.827291" />
  <m tm="" al="1673" lg="6.624088" lt="45.827378" />
  <m tm="" al="1660" lg="6.625128" lt="45.827335" />
  <m tm="" al="1657" lg="6.625359" lt="45.827443" />
  <m tm="" al="1655" lg="6.625804" lt="45.827390" />
  <m tm="" al="1650" lg="6.625988" lt="45.827912" />
  <m tm="" al="1647" lg="6.626059" lt="45.827756" />
  <m tm="" al="1646" lg="6.626423" lt="45.828238" />
  <m tm="" al="1646" lg="6.626983" lt="45.828392" />
  <m tm="" al="1634" lg="6.626898" lt="45.828274" />
  <m tm="" al="1586" lg="6.626536" lt="45.828443" />
  <m tm="" al="1591" lg="6.626615" lt="45.828403" />
  <m tm="" al="1588" lg="6.627359" lt="45.828720" />
  <m tm="" al="1583" lg="6.627979" lt="45.829262" />
  <m tm="" al="1582" lg="6.628123" lt="45.829911" />
  <m tm="" al="1579" lg="6.628785" lt="45.830819" />
  <m tm="" al="1579" lg="6.629041" lt="45.831030" />
  <m tm="" al="1526" lg="6.629083" lt="45.831194" />
  <m tm="" al="1518" lg="6.629676" lt="45.831127" />
  <m tm="" al="1509" lg="6.630313" lt="45.831423" />
  <m tm="" al="1501" lg="6.630994" lt="45.831488" />
  <m tm="" al="1491" lg="6.632118" lt="45.831874" />
  <m tm="" al="1484" lg="6.632447" lt="45.831891" />
  <m tm="" al="1472" lg="6.633153" lt="45.832174" />
  <m tm="" al="1457" lg="6.633702" lt="45.832622" />
  <m tm="" al="1446" lg="6.634108" lt="45.833198" />
  <m tm="" al="1439" lg="6.634549" lt="45.833500" />
  <m tm="" al="1412" lg="6.635683" lt="45.832928" />
  <m tm="" al="1400" lg="6.636186" lt="45.832955" />
  <m tm="" al="1399" lg="6.635912" lt="45.832699" />
  <m tm="" al="1396" lg="6.635699" lt="45.832330" />
  <m tm="" al="1460" lg="6.633431" lt="45.829946" />
  <m tm="" al="1521" lg="6.631934" lt="45.828083" />
  <m tm="" al="1876" lg="6.622737" lt="45.817276" />
  <m tm="" al="1876" lg="6.622819" lt="45.816905" />
  <m tm="" al="1870" lg="6.622738" lt="45.816287" />
  <m tm="" al="1867" lg="6.622899" lt="45.816045" />
  <m tm="" al="1837" lg="6.624661" lt="45.816268" />
  <m tm="" al="1829" lg="6.625741" lt="45.816741" />
  <m tm="" al="1822" lg="6.627348" lt="45.817165" />
  <m tm="" al="1821" lg="6.628581" lt="45.818284" />
  <m tm="" al="1812" lg="6.628737" lt="45.818545" />
  <m tm="" al="1736" lg="6.629712" lt="45.818902" />
  <m tm="" al="1720" lg="6.631869" lt="45.820297" />
  <m tm="" al="1715" lg="6.632469" lt="45.821005" />
  <m tm="" al="1705" lg="6.632846" lt="45.821262" />
  <m tm="" al="1699" lg="6.632880" lt="45.821523" />
  <m tm="" al="1686" lg="6.634364" lt="45.822553" />
  <m tm="" al="1625" lg="6.634459" lt="45.822942" />
  <m tm="" al="1629" lg="6.634376" lt="45.823015" />
  <m tm="" al="1623" lg="6.634671" lt="45.823118" />
  <m tm="" al="1613" lg="6.635028" lt="45.823580" />
  <m tm="" al="1601" lg="6.635386" lt="45.823844" />
  <m tm="" al="1589" lg="6.636307" lt="45.824151" />
  <m tm="" al="1573" lg="6.636573" lt="45.824961" />
  <m tm="" al="1533" lg="6.638105" lt="45.826215" />
  <m tm="" al="1519" lg="6.638220" lt="45.826904" />
  <m tm="" al="1504" lg="6.637939" lt="45.827721" />
  <m tm="" al="1485" lg="6.637241" lt="45.828883" />
  <m tm="" al="1479" lg="6.637040" lt="45.829081" />
  <m tm="" al="1469" lg="6.636768" lt="45.829004" />
  <m tm="" al="1464" lg="6.636683" lt="45.829477" />
  <m tm="" al="1465" lg="6.636376" lt="45.829615" />
  <m tm="" al="1461" lg="6.636482" lt="45.830241" />
  <m tm="" al="1445" lg="6.635787" lt="45.831002" />
  <m tm="" al="1445" lg="6.635770" lt="45.831187" />
  <m tm="" al="1440" lg="6.636132" lt="45.831697" />
  <m tm="" al="1437" lg="6.636275" lt="45.832087" />
  <m tm="" al="1426" lg="6.636674" lt="45.832479" />
  <m tm="" al="1409" lg="6.636476" lt="45.832903" />
  <m tm="" al="1405" lg="6.636411" lt="45.832868" />
  <m tm="" al="1405" lg="6.636445" lt="45.833004" />
  <m tm="" al="1387" lg="6.636409" lt="45.832847" />
  <m tm="" al="1384" lg="6.635944" lt="45.832844" />
  <m tm="" al="1389" lg="6.635936" lt="45.832743" />
  <m tm="" al="1846" lg="6.623074" lt="45.817561" />
  <m tm="" al="1846" lg="6.623003" lt="45.817874" />
  <m tm="" al="1863" lg="6.622695" lt="45.817016" />
  <m tm="" al="1857" lg="6.622721" lt="45.816130" />
  <m tm="" al="1848" lg="6.623329" lt="45.815106" />
  <m tm="" al="1837" lg="6.623982" lt="45.814370" />
  <m tm="" al="1837" lg="6.624062" lt="45.813954" />
  <m tm="" al="1826" lg="6.624483" lt="45.813230" />
  <m tm="" al="1822" lg="6.624989" lt="45.812805" />
  <m tm="" al="1816" lg="6.625512" lt="45.812578" />
  <m tm="" al="1802" lg="6.627214" lt="45.812594" />
  <m tm="" al="1794" lg="6.628120" lt="45.812764" />
  <m tm="" al="1787" lg="6.628296" lt="45.812914" />
  <m tm="" al="1772" lg="6.628114" lt="45.812923" />
  <m tm="" al="1767" lg="6.628632" lt="45.813560" />
  <m tm="" al="1762" lg="6.628724" lt="45.813991" />
  <m tm="" al="1760" lg="6.627974" lt="45.814271" />
  <m tm="" al="1758" lg="6.627894" lt="45.814543" />
  <m tm="" al="1747" lg="6.629011" lt="45.815394" />
  <m tm="" al="1716" lg="6.628985" lt="45.815302" />
  <m tm="" al="1699" lg="6.629075" lt="45.815310" />
  <m tm="" al="1690" lg="6.629203" lt="45.815467" />
  <m tm="" al="1689" lg="6.629298" lt="45.815437" />
  <m tm="" al="1693" lg="6.629559" lt="45.815588" />
  <m tm="" al="1693" lg="6.629897" lt="45.815469" />
  <m tm="" al="1885" lg="6.627694" lt="45.810870" />
  <m tm="" al="1893" lg="6.627578" lt="45.810430" />
  <m tm="" al="1898" lg="6.627770" lt="45.810360" />
  <m tm="" al="1895" lg="6.627994" lt="45.810048" />
  <m tm="" al="1897" lg="6.628832" lt="45.809743" />
  <m tm="" al="1895" lg="6.629137" lt="45.809692" />
  <m tm="" al="1888" lg="6.629711" lt="45.809903" />
  <m tm="" al="1879" lg="6.630224" lt="45.809843" />
  <m tm="" al="1866" lg="6.631323" lt="45.809055" />
  <m tm="" al="1864" lg="6.631032" lt="45.808693" />
  <m tm="" al="1863" lg="6.631652" lt="45.808007" />
  <m tm="" al="1861" lg="6.631904" lt="45.807945" />
  <m tm="" al="1859" lg="6.632269" lt="45.807592" />
  <m tm="" al="1855" lg="6.632862" lt="45.807264" />
  <m tm="" al="1852" lg="6.633343" lt="45.807118" />
  <m tm="" al="1842" lg="6.634360" lt="45.807072" />
  <m tm="" al="1830" lg="6.635115" lt="45.807467" />
  <m tm="" al="1814" lg="6.635729" lt="45.808106" />
  <m tm="" al="1805" lg="6.636011" lt="45.808617" />
  <m tm="" al="1799" lg="6.636076" lt="45.808964" />
  <m tm="" al="1786" lg="6.637881" lt="45.808847" />
  <m tm="" al="1784" lg="6.638146" lt="45.808494" />
  <m tm="" al="1776" lg="6.638765" lt="45.808890" />
  <m tm="" al="1773" lg="6.639098" lt="45.809277" />
  <m tm="" al="1762" lg="6.640051" lt="45.809751" />
  <m tm="" al="1759" lg="6.640765" lt="45.809684" />
  <m tm="" al="1757" lg="6.640869" lt="45.809825" />
  <m tm="" al="1746" lg="6.641726" lt="45.810312" />
  <m tm="" al="1740" lg="6.642197" lt="45.810826" />
  <m tm="" al="1724" lg="6.642512" lt="45.811888" />
  <m tm="" al="1716" lg="6.643204" lt="45.812381" />
  <m tm="" al="1713" lg="6.643410" lt="45.811863" />
  <m tm="" al="1712" lg="6.643675" lt="45.811664" />
  <m tm="" al="1711" lg="6.643810" lt="45.811872" />
  <m tm="" al="1706" lg="6.644158" lt="45.812035" />
  <m tm="" al="1698" lg="6.644883" lt="45.812226" />
  <m tm="" al="1690" lg="6.644910" lt="45.812141" />
  <m tm="" al="1674" lg="6.644351" lt="45.812327" />
  <m tm="" al="1662" lg="6.645038" lt="45.812034" />
  <m tm="" al="1662" lg="6.644372" lt="45.812341" />
  <m tm="" al="1662" lg="6.644555" lt="45.812402" />
  <m tm="" al="1662" lg="6.645124" lt="45.812168" />
  <m tm="" al="1662" lg="6.645128" lt="45.812252" />
  <m tm="" al="1661" lg="6.644458" lt="45.812659" />
  <m tm="" al="1660" lg="6.644872" lt="45.812712" />
  <m tm="" al="1652" lg="6.645400" lt="45.813413" />
  <m tm="" al="1633" lg="6.646386" lt="45.813323" />
  <m tm="" al="1631" lg="6.646600" lt="45.813503" />
  <m tm="" al="1631" lg="6.647495" lt="45.813382" />
  <m tm="" al="1631" lg="6.647990" lt="45.813502" />
  <m tm="" al="1622" lg="6.649855" lt="45.814309" />
  <m tm="" al="1571" lg="6.650661" lt="45.814390" />
  <m tm="" al="1566" lg="6.651050" lt="45.814670" />
  <m tm="" al="1559" lg="6.651379" lt="45.815094" />
  <m tm="" al="1546" lg="6.651934" lt="45.816169" />
  <m tm="" al="1508" lg="6.651553" lt="45.816581" />
  <m tm="" al="1506" lg="6.652152" lt="45.817088" />
  <m tm="" al="1505" lg="6.651677" lt="45.817279" />
  <m tm="" al="1501" lg="6.652050" lt="45.817282" />
  <m tm="" al="1502" lg="6.652229" lt="45.817180" />
  <m tm="" al="1508" lg="6.651843" lt="45.817303" />
  <m tm="" al="1499" lg="6.652040" lt="45.817218" />
  <m tm="" al="1499" lg="6.652296" lt="45.817265" />
  <m tm="" al="1499" lg="6.651696" lt="45.817288" />
  <m tm="" al="1497" lg="6.651714" lt="45.817366" />
  <m tm="" al="1499" lg="6.651668" lt="45.817271" />
  <m tm="" al="1501" lg="6.652247" lt="45.817722" />
  <m tm="" al="1501" lg="6.651349" lt="45.818711" />
  <m tm="" al="1501" lg="6.651318" lt="45.819113" />
  <m tm="" al="1501" lg="6.651074" lt="45.819206" />
  <m tm="" al="1501" lg="6.651042" lt="45.819429" />
  <m tm="" al="1501" lg="6.651128" lt="45.819275" />
  <m tm="" al="1501" lg="6.651250" lt="45.819317" />
  <m tm="" al="1499" lg="6.651394" lt="45.819644" />
  <m tm="" al="1471" lg="6.651413" lt="45.820253" />
  <m tm="" al="1474" lg="6.651592" lt="45.820024" />
  <m tm="" al="1477" lg="6.651228" lt="45.819082" />
  <m tm="" al="1477" lg="6.651514" lt="45.818609" />
  <m tm="" al="1499" lg="6.651760" lt="45.817367" />
  <m tm="" al="1493" lg="6.652230" lt="45.817282" />
  <m tm="" al="1504" lg="6.651689" lt="45.817239" />
  <m tm="" al="1572" lg="6.649455" lt="45.814136" />
  <m tm="" al="1764" lg="6.645595" lt="45.809064" />
  <m tm="" al="1774" lg="6.645205" lt="45.809093" />
  <m tm="" al="1772" lg="6.645210" lt="45.809187" />
  <m tm="" al="1756" lg="6.646159" lt="45.809723" />
  <m tm="" al="1755" lg="6.646321" lt="45.809714" />
  <m tm="" al="1747" lg="6.646922" lt="45.809991" />
  <m tm="" al="1716" lg="6.647810" lt="45.809996" />
  <m tm="" al="1711" lg="6.648322" lt="45.810341" />
  <m tm="" al="1701" lg="6.648502" lt="45.810702" />
  <m tm="" al="1670" lg="6.649434" lt="45.811858" />
  <m tm="" al="1658" lg="6.649503" lt="45.812280" />
  <m tm="" al="1649" lg="6.650001" lt="45.812950" />
  <m tm="" al="1643" lg="6.650075" lt="45.813210" />
  <m tm="" al="1636" lg="6.649973" lt="45.813384" />
  <m tm="" al="1624" lg="6.650204" lt="45.813545" />
  <m tm="" al="1614" lg="6.650392" lt="45.813962" />
  <m tm="" al="1607" lg="6.650626" lt="45.814209" />
  <m tm="" al="1605" lg="6.650602" lt="45.814358" />
  <m tm="" al="1597" lg="6.650867" lt="45.814601" />
  <m tm="" al="1561" lg="6.650904" lt="45.815073" />
  <m tm="" al="1553" lg="6.651637" lt="45.815137" />
  <m tm="" al="1549" lg="6.651616" lt="45.815377" />
  <m tm="" al="1546" lg="6.651975" lt="45.815852" />
  <m tm="" al="1510" lg="6.651967" lt="45.816134" />
  <m tm="" al="1508" lg="6.651771" lt="45.816273" />
  <m tm="" al="1507" lg="6.652136" lt="45.816483" />
  <m tm="" al="1499" lg="6.651927" lt="45.817098" />
  <m tm="" al="1498" lg="6.651972" lt="45.817393" />
  <m tm="" al="1507" lg="6.651661" lt="45.817271" />
  <m tm="" al="1507" lg="6.651358" lt="45.816742" />
  <m tm="" al="1570" lg="6.649573" lt="45.814332" />
  <m tm="" al="1772" lg="6.645501" lt="45.808996" />
  <m tm="" al="1766" lg="6.645044" lt="45.809366" />
  <m tm="" al="1749" lg="6.644682" lt="45.810167" />
  <m tm="" al="1736" lg="6.644818" lt="45.810415" />
  <m tm="" al="1732" lg="6.645204" lt="45.810423" />
  <m tm="" al="1717" lg="6.645265" lt="45.810967" />
  <m tm="" al="1709" lg="6.645145" lt="45.810969" />
  <m tm="" al="1691" lg="6.645395" lt="45.812024" />
  <m tm="" al="1684" lg="6.644912" lt="45.812545" />
  <m tm="" al="1671" lg="6.644860" lt="45.813267" />
  <m tm="" al="1640" lg="6.645627" lt="45.815041" />
  <m tm="" al="1626" lg="6.645871" lt="45.816144" />
  <m tm="" al="1619" lg="6.645438" lt="45.816559" />
  <m tm="" al="1611" lg="6.645318" lt="45.816983" />
  <m tm="" al="1605" lg="6.645378" lt="45.817317" />
  <m tm="" al="1600" lg="6.645244" lt="45.817759" />
  <m tm="" al="1580" lg="6.645241" lt="45.818579" />
  <m tm="" al="1574" lg="6.645129" lt="45.818855" />
  <m tm="" al="1550" lg="6.644332" lt="45.819636" />
  <m tm="" al="1548" lg="6.643984" lt="45.819693" />
  <m tm="" al="1546" lg="6.643643" lt="45.819624" />
  <m tm="" al="1539" lg="6.643307" lt="45.819025" />
  <m tm="" al="1538" lg="6.643242" lt="45.818599" />
  <m tm="" al="1538" lg="6.643005" lt="45.818605" />
  <m tm="" al="1494" lg="6.642142" lt="45.819485" />
  <m tm="" al="1492" lg="6.642243" lt="45.819672" />
  <m tm="" al="1492" lg="6.642195" lt="45.819912" />
  <m tm="" al="1489" lg="6.641855" lt="45.820001" />
  <m tm="" al="1678" lg="6.635195" lt="45.811707" />
  <m tm="" al="1888" lg="6.628628" lt="45.810187" />
  <m tm="" al="1885" lg="6.626544" lt="45.810814" />
  <m tm="" al="1880" lg="6.626046" lt="45.811188" />
  <m tm="" al="1855" lg="6.623617" lt="45.812104" />
  <m tm="" al="1851" lg="6.623526" lt="45.812516" />
  <m tm="" al="1848" lg="6.623603" lt="45.813021" />
  <m tm="" al="1843" lg="6.623848" lt="45.813811" />
  <m tm="" al="1837" lg="6.624289" lt="45.814499" />
  <m tm="" al="1824" lg="6.624161" lt="45.815537" />
  <m tm="" al="1819" lg="6.624241" lt="45.815994" />
  <m tm="" al="1810" lg="6.624717" lt="45.816398" />
  <m tm="" al="1807" lg="6.625162" lt="45.816608" />
  <m tm="" al="1799" lg="6.626606" lt="45.816997" />
  <m tm="" al="1797" lg="6.627118" lt="45.817248" />
  <m tm="" al="1795" lg="6.627378" lt="45.817572" />
  <m tm="" al="1780" lg="6.628280" lt="45.818281" />
  <m tm="" al="1770" lg="6.629245" lt="45.818558" />
  <m tm="" al="1746" lg="6.630576" lt="45.819248" />
  <m tm="" al="1738" lg="6.631083" lt="45.819645" />
  <m tm="" al="1731" lg="6.631330" lt="45.819997" />
  <m tm="" al="1719" lg="6.631994" lt="45.820619" />
  <m tm="" al="1712" lg="6.632350" lt="45.820816" />
  <m tm="" al="1701" lg="6.632429" lt="45.820758" />
  <m tm="" al="1700" lg="6.632401" lt="45.820851" />
  <m tm="" al="1681" lg="6.632683" lt="45.821066" />
  <m tm="" al="1675" lg="6.632758" lt="45.821451" />
  <m tm="" al="1664" lg="6.633133" lt="45.821876" />
  <m tm="" al="1658" lg="6.633455" lt="45.822481" />
  <m tm="" al="1661" lg="6.633558" lt="45.822340" />
  <m tm="" al="1657" lg="6.633575" lt="45.822550" />
  <m tm="" al="1652" lg="6.633146" lt="45.822728" />
  <m tm="" al="1640" lg="6.630862" lt="45.823045" />
  <m tm="" al="1632" lg="6.630522" lt="45.823181" />
  <m tm="" al="1630" lg="6.630554" lt="45.823090" />
  <m tm="" al="1888" lg="6.620238" lt="45.820192" />
  <m tm="" al="1883" lg="6.619332" lt="45.820603" />
  <m tm="" al="1871" lg="6.618195" lt="45.821278" />
  <m tm="" al="1864" lg="6.617383" lt="45.822227" />
  <m tm="" al="1864" lg="6.617316" lt="45.822605" />
  <m tm="" al="1856" lg="6.617823" lt="45.823924" />
  <m tm="" al="1855" lg="6.618039" lt="45.824172" />
  <m tm="" al="1850" lg="6.618581" lt="45.824468" />
  <m tm="" al="1847" lg="6.618699" lt="45.824688" />
  <m tm="" al="1836" lg="6.618606" lt="45.825356" />
  <m tm="" al="1822" lg="6.618695" lt="45.825945" />
  <m tm="" al="1815" lg="6.618510" lt="45.826352" />
  <m tm="" al="1808" lg="6.618067" lt="45.826892" />
  <m tm="" al="1799" lg="6.617375" lt="45.827469" />
  <m tm="" al="1780" lg="6.616724" lt="45.828412" />
  <m tm="" al="1769" lg="6.616315" lt="45.829228" />
  <m tm="" al="1761" lg="6.616278" lt="45.830073" />
  <m tm="" al="1757" lg="6.616418" lt="45.830286" />
  <m tm="" al="1747" lg="6.616165" lt="45.830287" />
  <m tm="" al="1740" lg="6.616024" lt="45.830606" />
  <m tm="" al="1735" lg="6.615674" lt="45.831027" />
  <m tm="" al="1733" lg="6.615539" lt="45.831436" />
  <m tm="" al="1724" lg="6.615544" lt="45.832011" />
  <m tm="" al="1722" lg="6.615684" lt="45.832420" />
  <m tm="" al="1721" lg="6.615636" lt="45.832661" />
  <m tm="" al="1715" lg="6.616212" lt="45.832925" />
  <m tm="" al="1710" lg="6.616375" lt="45.833315" />
  <m tm="" al="1709" lg="6.616356" lt="45.833464" />
  <m tm="" al="1705" lg="6.616114" lt="45.833667" />
  <m tm="" al="1687" lg="6.615909" lt="45.834790" />
  <m tm="" al="1671" lg="6.616455" lt="45.835674" />
  <m tm="" al="1662" lg="6.616481" lt="45.836192" />
  <m tm="" al="1589" lg="6.617379" lt="45.837826" />
  <m tm="" al="1590" lg="6.617189" lt="45.837831" />
  <m tm="" al="1582" lg="6.618085" lt="45.838237" />
  <m tm="" al="1576" lg="6.618514" lt="45.838563" />
  <m tm="" al="1543" lg="6.620274" lt="45.839351" />
  <m tm="" al="1521" lg="6.621252" lt="45.840098" />
  <m tm="" al="1517" lg="6.621471" lt="45.841194" />
  <m tm="" al="1500" lg="6.621972" lt="45.841467" />
  <m tm="" al="1495" lg="6.622005" lt="45.841756" />
  <m tm="" al="1414" lg="6.623217" lt="45.842222" />
  <m tm="" al="1394" lg="6.624338" lt="45.843005" />
  <m tm="" al="1389" lg="6.624777" lt="45.843092" />
  <m tm="" al="1374" lg="6.625505" lt="45.843482" />
  <m tm="" al="1368" lg="6.625633" lt="45.843764" />
  <m tm="" al="1365" lg="6.625795" lt="45.843805" />
  <m tm="" al="1349" lg="6.625835" lt="45.844587" />
  <m tm="" al="1340" lg="6.625615" lt="45.844891" />
  <m tm="" al="1331" lg="6.625656" lt="45.845050" />
  <m tm="" al="1314" lg="6.625260" lt="45.844804" />
  <m tm="" al="1317" lg="6.625738" lt="45.844959" />
  <m tm="" al="1308" lg="6.625431" lt="45.845399" />
  <m tm="" al="1309" lg="6.625773" lt="45.845285" />
  <m tm="" al="1328" lg="6.624913" lt="45.844713" />
  <m tm="" al="1395" lg="6.622646" lt="45.841957" />
  <m tm="" al="1411" lg="6.621094" lt="45.840932" />
  <m tm="" al="1414" lg="6.620596" lt="45.840795" />
  <m tm="" al="1431" lg="6.620925" lt="45.839935" />
  <m tm="" al="1540" lg="6.618724" lt="45.837509" />
  <m tm="" al="1566" lg="6.616588" lt="45.834963" />
  <m tm="" al="1607" lg="6.615800" lt="45.833895" />
  <m tm="" al="1744" lg="6.614088" lt="45.832191" />
  <m tm="" al="1752" lg="6.614019" lt="45.832216" />
  <m tm="" al="1759" lg="6.614257" lt="45.832253" />
  <m tm="" al="1741" lg="6.615667" lt="45.831886" />
  <m tm="" al="1733" lg="6.615646" lt="45.832309" />
  <m tm="" al="1729" lg="6.615895" lt="45.832708" />
  <m tm="" al="1720" lg="6.616364" lt="45.833169" />
  <m tm="" al="1715" lg="6.616194" lt="45.833368" />
  <m tm="" al="1703" lg="6.615473" lt="45.833773" />
  <m tm="" al="1697" lg="6.615814" lt="45.834047" />
  <m tm="" al="1690" lg="6.616883" lt="45.834378" />
  <m tm="" al="1684" lg="6.617394" lt="45.834355" />
  <m tm="" al="1631" lg="6.617943" lt="45.833932" />
  <m tm="" al="1615" lg="6.618730" lt="45.833928" />
  <m tm="" al="1610" lg="6.618994" lt="45.834244" />
  <m tm="" al="1608" lg="6.618974" lt="45.835164" />
  <m tm="" al="1607" lg="6.618780" lt="45.835725" />
  <m tm="" al="1607" lg="6.618898" lt="45.835897" />
  <m tm="" al="1605" lg="6.619236" lt="45.836073" />
  <m tm="" al="1572" lg="6.620627" lt="45.836152" />
  <m tm="" al="1565" lg="6.621026" lt="45.836306" />
  <m tm="" al="1560" lg="6.622264" lt="45.836399" />
  <m tm="" al="1560" lg="6.621995" lt="45.836793" />
  <m tm="" al="1554" lg="6.622365" lt="45.837108" />
  <m tm="" al="1536" lg="6.622704" lt="45.837647" />
  <m tm="" al="1470" lg="6.623403" lt="45.838047" />
  <m tm="" al="1460" lg="6.624182" lt="45.838165" />
  <m tm="" al="1454" lg="6.624586" lt="45.838340" />
  <m tm="" al="1450" lg="6.624784" lt="45.838937" />
  <m tm="" al="1440" lg="6.625791" lt="45.839283" />
  <m tm="" al="1434" lg="6.625885" lt="45.839475" />
  <m tm="" al="1432" lg="6.626291" lt="45.839688" />
  <m tm="" al="1425" lg="6.626078" lt="45.839788" />
  <m tm="" al="1401" lg="6.624933" lt="45.839829" />
  <m tm="" al="1395" lg="6.625403" lt="45.841826" />
  <m tm="" al="1383" lg="6.625302" lt="45.842730" />
  <m tm="" al="1379" lg="6.625144" lt="45.842913" />
  <m tm="" al="1362" lg="6.625405" lt="45.843708" />
  <m tm="" al="1351" lg="6.625786" lt="45.844052" />
  <m tm="" al="1344" lg="6.625827" lt="45.844481" />
  <m tm="" al="1336" lg="6.625719" lt="45.845004" />
  <m tm="" al="1324" lg="6.625713" lt="45.844892" />
  <m tm="" al="1312" lg="6.625854" lt="45.845039" />
  <m tm="" al="1311" lg="6.625700" lt="45.844789" />
  <m tm="" al="1310" lg="6.625964" lt="45.845460" />
  <m tm="" al="1307" lg="6.625932" lt="45.845842" />
  <m tm="" al="1302" lg="6.625587" lt="45.846061" />
  <m tm="" al="1293" lg="6.624237" lt="45.846025" />
  <m tm="" al="1273" lg="6.622596" lt="45.846673" />
  <m tm="" al="1247" lg="6.619969" lt="45.847376" />
  <m tm="" al="1226" lg="6.618507" lt="45.847286" />
  <m tm="" al="1215" lg="6.617588" lt="45.847533" />
  <m tm="" al="1199" lg="6.617075" lt="45.848413" />
  <m tm="" al="1196" lg="6.616718" lt="45.848744" />
  <m tm="" al="1192" lg="6.616421" lt="45.848839" />
  <m tm="" al="1188" lg="6.616279" lt="45.848750" />
  <m tm="" al="1185" lg="6.616261" lt="45.848541" />
  <m tm="" al="1295" lg="6.623541" lt="45.844954" />
  <m tm="" al="1308" lg="6.624405" lt="45.844403" />
  <m tm="" al="1309" lg="6.624641" lt="45.844345" />
  <m tm="" al="1316" lg="6.624667" lt="45.844404" />
  <m tm="" al="1322" lg="6.624166" lt="45.844932" />
  <m tm="" al="1314" lg="6.623072" lt="45.845556" />
  <m tm="" al="1306" lg="6.622911" lt="45.845967" />
  <m tm="" al="1302" lg="6.622728" lt="45.846057" />
  <m tm="" al="1294" lg="6.622090" lt="45.846056" />
  <m tm="" al="1285" lg="6.621500" lt="45.846257" />
  <m tm="" al="1281" lg="6.621048" lt="45.846441" />
  <m tm="" al="1265" lg="6.620059" lt="45.847162" />
  <m tm="" al="1259" lg="6.619651" lt="45.847277" />
  <m tm="" al="1239" lg="6.618069" lt="45.847391" />
  <m tm="" al="1214" lg="6.615982" lt="45.848569" />
  <m tm="" al="1207" lg="6.616169" lt="45.848795" />
  <m tm="" al="1195" lg="6.616236" lt="45.848567" />
  <m tm="" al="1235" lg="6.620694" lt="45.846316" />
  <m tm="" al="1234" lg="6.620278" lt="45.846387" />
  <m tm="" al="1286" lg="6.622703" lt="45.845292" />
  <m tm="" al="1326" lg="6.624318" lt="45.844388" />
  <m tm="" al="1324" lg="6.625598" lt="45.844782" />
  <m tm="" al="1321" lg="6.626025" lt="45.845465" />
  <m tm="" al="1319" lg="6.625890" lt="45.845575" />
  <m tm="" al="1315" lg="6.625319" lt="45.845191" />
  <m tm="" al="1310" lg="6.626410" lt="45.846399" />
  <m tm="" al="1292" lg="6.629804" lt="45.850893" />
  <m tm="" al="1292" lg="6.631807" lt="45.853256" />
  <m tm="" al="1286" lg="6.631761" lt="45.853760" />
  <m tm="" al="1290" lg="6.631706" lt="45.853713" />
  <m tm="" al="1291" lg="6.631819" lt="45.853399" />
  <m tm="" al="1290" lg="6.631711" lt="45.853335" />
  <m tm="" al="1289" lg="6.631794" lt="45.853415" />
  <m tm="" al="1288" lg="6.631784" lt="45.853293" />
  <m tm="" al="1281" lg="6.631726" lt="45.853475" />
  <m tm="" al="1281" lg="6.631530" lt="45.855025" />
  <m tm="" al="1274" lg="6.630834" lt="45.855300" />
  <m tm="" al="1271" lg="6.631272" lt="45.855493" />
  <m tm="" al="1271" lg="6.631386" lt="45.855686" />
  <m tm="" al="1275" lg="6.631075" lt="45.857094" />
  <m tm="" al="1273" lg="6.630964" lt="45.857153" />
  <p lg="6.692763" lt="45.829445" text="2353" />
  <p lg="6.837686" lt="45.933426" text="2525" />
  <p lg="6.911269" lt="45.772872" text="2624" />
  <p lg="6.959972" lt="45.947984" text="3275" />
  <p lg="6.889599" lt="45.879728" text="3700 - Start" />
  <p lg="6.886881" lt="45.879252" text="3800" />
  <p lg="6.887326" lt="45.878653" text="3842" />
  <p lg="6.630327" lt="45.857261" text="Appartment 1" />
  <p lg="6.868063" lt="45.922224" text="Appartment 2" />
  <p lg="6.869953" lt="45.918245" text="Base A Du Midi" />
  <p lg="6.863368" lt="45.924222" text="Base Brevet" />
  <p lg="6.781409" lt="45.894176" text="Base Houches" />
  <p lg="6.632022" lt="45.853767" text="Base Megeve" />
  <p lg="6.955837" lt="46.013503" text="Cafe Charamill" />
  <p lg="6.700992" lt="45.851380" text="Cafe Choucas" />
  <p lg="6.691598" lt="45.840035" text="Cafe Mont Joly" />
  <p lg="2.304271" lt="48.761963" text="Croix Station" />
  <p lg="6.938170" lt="45.894679" text="Cross of Pistes" />
  <p lg="2.340767" lt="48.857183" text="Тайник 'Heart of Paris'. Точка 1" url="http://www.geocaching.com/seek/cache_details.aspx?guid=5f016a77-8972-4643-b5f2-7fb23a0641fa" urlname="Страница тайника" />
  <p lg="2.342283" lt="48.856583" text="Тайник 'Heart of Paris'. Точка 2" url="http://www.geocaching.com/seek/cache_details.aspx?guid=5f016a77-8972-4643-b5f2-7fb23a0641fa" urlname="Страница тайника" />
  <p lg="2.347317" lt="48.855833" text="Тайник 'Heart of Paris'. Точка 3" url="http://www.geocaching.com/seek/cache_details.aspx?guid=5f016a77-8972-4643-b5f2-7fb23a0641fa" urlname="Страница тайника" />
  <p lg="2.348767" lt="48.853517" text="Тайник 'Heart of Paris'. Точка 4" url="http://www.geocaching.com/seek/cache_details.aspx?guid=5f016a77-8972-4643-b5f2-7fb23a0641fa" urlname="Страница тайника" />
  <p lg="2.352333" lt="48.851833" text="Тайник 'Heart of Paris'. Точка 5" url="http://www.geocaching.com/seek/cache_details.aspx?guid=5f016a77-8972-4643-b5f2-7fb23a0641fa" urlname="Страница тайника" />
  <p lg="2.350567" lt="48.854767" text="Тайник 'Heart of Paris'. Точка 6" url="http://www.geocaching.com/seek/cache_details.aspx?guid=5f016a77-8972-4643-b5f2-7fb23a0641fa" urlname="Страница тайника" />
  <p lg="6.916988" lt="45.930573" text="Train Station" />
</markers>